korean_lunar_calendar/__init__.py
korean_lunar_calendar/korean_lunar_calendar.py
korean_lunar_calendar-0.2.0.dist-info/METADATA
korean_lunar_calendar-0.2.0.dist-info/WHEEL
korean_lunar_calendar-0.2.0.dist-info/top_level.txt
korean_lunar_calendar-0.2.0.dist-info/RECORD
