Metadata-Version: 2.1
Name: korean-lunar-calendar
Version: 0.2.0
Summary: Korean Lunar Calendar
Home-page: https://github.com/usingsky/korean_lunar_calendar_py
Author: Jinil Lee
Author-email: usingsky@gmail.com
Maintainer: Jinil Lee
Maintainer-email: usingsky@gmail.com
License: MIT
Keywords: calendar,korean,lunar
Platform: UNKNOWN
Classifier: Development Status :: 3 - Alpha
Classifier: Intended Audience :: Developers
Classifier: Intended Audience :: End Users/Desktop
Classifier: Topic :: Software Development :: Libraries
Classifier: License :: OSI Approved :: MIT License
Classifier: Operating System :: OS Independent
Classifier: Programming Language :: Python :: 2
Classifier: Programming Language :: Python :: 2.7
Classifier: Programming Language :: Python :: 3
Classifier: Programming Language :: Python :: 3.4
Classifier: Programming Language :: Python :: 3.5
Classifier: Programming Language :: Python :: 3.6
Classifier: Programming Language :: Python :: 3.7
